diskinfo/__init__.py
diskinfo/demo.py
diskinfo/disk.py
diskinfo/diskinfo.py
diskinfo/disksmart.py
diskinfo/disktype.py
diskinfo/partition.py
diskinfo/utils.py
diskinfo-3.1.2.dist-info/LICENSE
diskinfo-3.1.2.dist-info/METADATA
diskinfo-3.1.2.dist-info/WHEEL
diskinfo-3.1.2.dist-info/top_level.txt
diskinfo-3.1.2.dist-info/RECORD
