Metadata-Version: 2.1
Name: diskinfo
Version: 3.1.2
Summary: Disk information Python library for Linux
Author-email: Peter Sulyok <peter@sulyok.net>
License: MIT License
Project-URL: Homepage, https://github.com/petersulyok/diskinfo
Project-URL: Documentation, https://diskinfo.readthedocs.io/en/latest/index.html
Keywords: disk,linux
Classifier: Programming Language :: Python :: 3.8
Classifier: Programming Language :: Python :: 3.9
Classifier: Programming Language :: Python :: 3.10
Classifier: Programming Language :: Python :: 3.11
Classifier: Programming Language :: Python :: 3.12
Classifier: License :: OSI Approved :: MIT License
Classifier: Operating System :: POSIX :: Linux
Classifier: Topic :: System :: Hardware
Classifier: Development Status :: 5 - Production/Stable
Requires-Python: >=3.8
License-File: LICENSE
Requires-Dist: pySMART >=1.3.0
